{"Delivery_Out":[{"WebDocKey":"15322","WebDocNum":"110002712","DODate":"2018-03-21","SAPExpDelDate":"2018-03-21","DateGap":"0","DONo":"1009011","Series":"8","DefDocType":"WIS","TransmitDate":"1900-01-01","DOTransDate":"1900-01-01","DOStat":"O","CardCode":"C11106","CardName":"JBL ENTERPRISE","PepsiDRNo":" ","Location":"Pick-Up\/Ex-R2 Warehouse\r\r \rPHILIPPINES","MotherPO":"AMC 00819","TruckCode":"PICK","TruckCo":"Pick up","WhsCode":"120202","Source":"R2 WAREHOUSE","U_Whse_Type":"W","U_SADocKey":"1960","U_SADocNo":"11001157","U_SADocLine1":"1","U_SATransNo":"1","U_SATransTyp":"SO","ItemCode":"0220731","Dscription":"Lopez Standard Refined","UnitMsr":"lkg","DOQty":"2000.00","B1UnservedQty":"2000.00","Served":"0.00","TransPO":"AMC 00819","SlpCode":"3","AE":"Alex Collarin","DORemarks":"First 15days FREE Php0.25\/bag\/day in excess of 15days\rGenerated for Sales Allocation Document# 11001157.","UpdateDate":"2018-03-21","Quantity":"550.000","PostDate":"2018-03-27","BaseLine":"0","BaseEntry":"9054","BaseType":"17","WebRemarks":"","Transtype":"DT_04","BatchCode":"","WebWhsCode":"5","WebWhsName":"R2 WAREHOUSE","SAPWhsCode":"120202","SAPWhsName":"R2 WAREHOUSE","Remarks":"","DRRef":"146821","U_DO":"148051"}]}