{"Delivery_Out":[{"WebDocKey":"6576","WebDocNum":"110001000","DODate":"2017-10-26","SAPExpDelDate":"2017-10-30","DateGap":"4","DONo":"1004138","Series":"8","DefDocType":"DR","TransmitDate":"1900-01-01","DOTransDate":"1900-01-01","DOStat":"O","CardCode":"C10500","CardName":"ARC Refreshments Corporation","PepsiDRNo":" ","Location":"SAN FERNANDO PAMPANGA\r\r \rPHILIPPINES","MotherPO":"15370","TruckCode":"","TruckCo":"WEI","WhsCode":"120202","Source":"R2 WAREHOUSE","U_Whse_Type":"","U_SADocKey":"747","U_SADocNo":"6343","U_SADocLine1":"2","U_SATransNo":"24","U_SATransTyp":"SO","ItemCode":"0220746B","Dscription":"Lopez Premium Refined B","UnitMsr":"lkg","DOQty":"750.00","B1UnservedQty":"750.00","Served":"0.00","TransPO":"15370","SlpCode":"19","AE":"Brian Abanto","DORemarks":"Max of 10 batches during milling and 12 to 15 during off mill\rGenerated for Sales Allocation Document# 6343.","UpdateDate":"2017-10-26","Quantity":"750.000","PostDate":"2017-10-30","BaseLine":"0","BaseEntry":"4162","BaseType":"17","WebRemarks":"Max of 10 batches during milling and 12 to 15 during off mill\nGenerated for Sales Allocation Document# 6343.","Transtype":"DT_04","BatchCode":"","WebWhsCode":"5","WebWhsName":"R2 WAREHOUSE","SAPWhsCode":"120202","SAPWhsName":"R2 WAREHOUSE","Remarks":"","DRRef":"0052068","U_DO":"143542"}]}