{"Delivery_Out":[{"WebDocKey":"5314","WebDocNum":"110000749","DODate":"2017-09-28","SAPExpDelDate":"2017-09-29","DateGap":"1","DONo":"1003226","Series":"8","DefDocType":"WIS","TransmitDate":"1900-01-01","DOTransDate":"1900-01-01","DOStat":"O","CardCode":"C11106","CardName":"JBL ENTERPRISE","PepsiDRNo":" ","Location":"Pick-Up\/Ex-R2 Warehouse\r\r \rPHILIPPINES","MotherPO":"AMC 00573","TruckCode":"","TruckCo":"PICK UP","WhsCode":"120202","Source":"R2 WAREHOUSE","U_Whse_Type":"","U_SADocKey":"871","U_SADocNo":"11000458","U_SADocLine1":"1","U_SATransNo":"1","U_SATransTyp":"SO","ItemCode":"0220731","Dscription":"Lopez Standard Refined","UnitMsr":"lkg","DOQty":"1000.00","B1UnservedQty":"1000.00","Served":"0.00","TransPO":"AMC 00573","SlpCode":"3","AE":"Alex Collarin","DORemarks":"MR. PEPE LEPITIN\rFirst 15days FREE\rPhp0.25\/bag\/day in excess of 15 days. Generated for Sales Allocation Document# 11000458.","UpdateDate":"2017-09-28","Quantity":"500.000","PostDate":"2017-10-05","BaseLine":"0","BaseEntry":"3244","BaseType":"17","WebRemarks":"","Transtype":"DT_04","BatchCode":"","WebWhsCode":"5","WebWhsName":"R2 WAREHOUSE","SAPWhsCode":"120202","SAPWhsName":"R2 WAREHOUSE","Remarks":"","DRRef":"145848","U_DO":"142700"}]}